{
  "boundingVolume": {
    "region": [
      0.151768224,
      0.887023506,
      0.151864842,
      0.887120264,
      252.8,
      272.2
    ]
  },
  "geometricError": 0.0,
  "content": {
    "boundingVolume": {
      "region": [
        0.151846129,
        0.887023506,
        0.151864842,
        0.887062388,
        252.8,
        272.2
      ]
    },
    "uri": "15/34351/7131.b3dm"
  },
  "properties": {
    "externalReference externalObjectName": {
      "valueType": "STRING"
    },
    "DatenquelleDachhoehe": {
      "valueType": "STRING"
    },
    "Grundrissaktualitaet": {
      "valueType": "STRING"
    },
    "Gemeindeschluessel": {
      "valueType": "STRING"
    },
    "DatenquelleLage": {
      "valueType": "STRING"
    },
    "measuredHeight": {
      "valueType": "DOUBLE",
      "minimum": 1.789,
      "maximum": 11.16
    },
    "DatenquelleBodenhoehe": {
      "valueType": "STRING"
    },
    "roofType": {
      "valueType": "STRING"
    },
    "function": {
      "valueType": "STRING"
    },
    "creationDate": {
      "valueType": "STRING"
    },
    "Geometrietyp2DReferenz": {
      "valueType": "STRING"
    }
  }
}